Metadata-Version: 2.1
Name: raname
Version: 0.1
Summary: Random Name Generator | Use Free APIs
Author: Itsaoda
Author-email: febyzamsee@gmail.com
Classifier: Development Status :: 3 - Alpha
Classifier: Intended Audience :: Developers
Classifier: Topic :: Software Development :: Libraries :: Python Modules
Classifier: License :: OSI Approved :: MIT License
Classifier: Programming Language :: Python :: 3.11
